eazyml_dq/__init__.py
eazyml_dq/Darwin_arm64/__init__.py
eazyml_dq/Darwin_arm64/eazyml_dq/__init__.cpython-310-darwin.so
eazyml_dq/Darwin_arm64/eazyml_dq/__init__.cpython-311-darwin.so
eazyml_dq/Darwin_arm64/eazyml_dq/__init__.cpython-312-darwin.so
eazyml_dq/Darwin_arm64/eazyml_dq/__init__.cpython-38-darwin.so
eazyml_dq/Darwin_arm64/eazyml_dq/__init__.cpython-39-darwin.so
eazyml_dq/Darwin_arm64/eazyml_dq/client.cpython-310-darwin.so
eazyml_dq/Darwin_arm64/eazyml_dq/client.cpython-311-darwin.so
eazyml_dq/Darwin_arm64/eazyml_dq/client.cpython-312-darwin.so
eazyml_dq/Darwin_arm64/eazyml_dq/client.cpython-38-darwin.so
eazyml_dq/Darwin_arm64/eazyml_dq/client.cpython-39-darwin.so
eazyml_dq/Darwin_arm64/eazyml_dq/globals/__init__.cpython-310-darwin.so
eazyml_dq/Darwin_arm64/eazyml_dq/globals/__init__.cpython-311-darwin.so
eazyml_dq/Darwin_arm64/eazyml_dq/globals/__init__.cpython-312-darwin.so
eazyml_dq/Darwin_arm64/eazyml_dq/globals/__init__.cpython-38-darwin.so
eazyml_dq/Darwin_arm64/eazyml_dq/globals/__init__.cpython-39-darwin.so
eazyml_dq/Darwin_arm64/eazyml_dq/globals/config.cpython-310-darwin.so
eazyml_dq/Darwin_arm64/eazyml_dq/globals/config.cpython-311-darwin.so
eazyml_dq/Darwin_arm64/eazyml_dq/globals/config.cpython-312-darwin.so
eazyml_dq/Darwin_arm64/eazyml_dq/globals/config.cpython-38-darwin.so
eazyml_dq/Darwin_arm64/eazyml_dq/globals/config.cpython-39-darwin.so
eazyml_dq/Darwin_arm64/eazyml_dq/globals/config_data_quality.cpython-310-darwin.so
eazyml_dq/Darwin_arm64/eazyml_dq/globals/config_data_quality.cpython-311-darwin.so
eazyml_dq/Darwin_arm64/eazyml_dq/globals/config_data_quality.cpython-312-darwin.so
eazyml_dq/Darwin_arm64/eazyml_dq/globals/config_data_quality.cpython-38-darwin.so
eazyml_dq/Darwin_arm64/eazyml_dq/globals/config_data_quality.cpython-39-darwin.so
eazyml_dq/Darwin_arm64/eazyml_dq/globals/footer_var.cpython-310-darwin.so
eazyml_dq/Darwin_arm64/eazyml_dq/globals/footer_var.cpython-311-darwin.so
eazyml_dq-0.0.26.dist-info/LICENSE
eazyml_dq-0.0.26.dist-info/METADATA
eazyml_dq-0.0.26.dist-info/WHEEL
eazyml_dq-0.0.26.dist-info/top_level.txt
eazyml_dq-0.0.26.dist-info/RECORD
