Metadata-Version: 2.1
Name: eazyml-dq
Version: 0.0.26
Summary: eazyml-data-quality provides APIs for comprehensive data quality assessment, including bias detection, outlier identification, and data drift analysis.
Home-page: https://eazyml.com/
Author: Eazyml
Author-email: admin@ipsoftlabs.com
Project-URL: Documentation, https://docs.eazyml.com/
Project-URL: Homepage, https://eazyml.com/
Project-URL: Contact Us, https://eazyml.com/trust-in-ai
Project-URL: eazyml, https://pypi.org/project/eazyml/
Project-URL: eazyml-cf, https://pypi.org/project/eazyml-cf/
Project-URL: eazyml-xai, https://pypi.org/project/eazyml-xai/
Project-URL: eazyml-xai-image, https://pypi.org/project/eazyml-xai-image/
Project-URL: eazyml-augi, https://pypi.org/project/eazyml-augi/
Project-URL: eazyml-dq, https://pypi.org/project/eazyml-dq/
Keywords: data-quality,bias-detection,outlier-detection,data-drift,model-drift,missing-values,correlation-analysis,data-imputation,data-balance,data-quality-tests,ml-api
Classifier: Development Status :: 5 - Production/Stable
Classifier: License :: Other/Proprietary License
Classifier: Intended Audience :: Developers
Classifier: Intended Audience :: Science/Research
Classifier: Intended Audience :: Information Technology
Classifier: Programming Language :: Python :: 3.8
Classifier: Programming Language :: Python :: 3.9
Classifier: Programming Language :: Python :: 3.10
Classifier: Programming Language :: Python :: 3.11
Classifier: Programming Language :: Python :: 3.12
Classifier: Topic :: Scientific/Engineering :: Artificial Intelligence
Classifier: Operating System :: Unix
Classifier: Operating System :: Microsoft :: Windows
Requires-Python: >=3.7
License-File: LICENSE
Requires-Dist: pandas (==2.0.3)
Requires-Dist: scikit-learn (==1.3.2)
Requires-Dist: numpy (==1.24.3)
Requires-Dist: openpyxl
Requires-Dist: flask
Requires-Dist: getmac
Requires-Dist: cryptography
Requires-Dist: PyYAML
Requires-Dist: requests
